pyfinra/__init__.py
pyfinra/financials/__init__.py
pyfinra/financials/finStatementsDictToDf.py
pyfinra/financials/financialStatements.py
pyfinra/financials/quote.py
pyfinra/financials/tools/__init__.py
pyfinra/financials/tools/cookieGetter.py
pyfinra/financials/tools/finraStockID.py
pyfinra/financials/tools/get_access.py
pyfinra/ticker.py
pyfinra-0.2.2.dist-info/WHEEL
pyfinra-0.2.2.dist-info/METADATA
pyfinra-0.2.2.dist-info/RECORD
